falcon_ml_xgboost/__init__.py
falcon_ml_xgboost/model.py
falcon_ml_xgboost/task_configs.py
falcon_ml_xgboost-0.2.0.dist-info/METADATA
falcon_ml_xgboost-0.2.0.dist-info/WHEEL
falcon_ml_xgboost-0.2.0.dist-info/top_level.txt
falcon_ml_xgboost-0.2.0.dist-info/RECORD
